MAna/__init__.py
MAna/analysis/__init__.py
MAna/analysis/visualizations.py
MAna/data/__init__.py
MAna/data/data_cleaning.py
MAna/data/data_io.py
MAna/modeling/__init__.py
MAna/modeling/data_preprocessing.py
MAna/modeling/model_evaluation.py
MAna/modeling/modeling.py
MAna/modeling/visualizations.py
M_Ana_package-0.0.6.dist-info/LICENCE.txt
M_Ana_package-0.0.6.dist-info/METADATA
M_Ana_package-0.0.6.dist-info/WHEEL
M_Ana_package-0.0.6.dist-info/top_level.txt
M_Ana_package-0.0.6.dist-info/RECORD
