Metadata-Version: 2.1
Name: M-Ana-package
Version: 0.0.6
Summary: A Python Package for Data Manipulation and Analysis
Home-page: 
Author: M_A
Keywords: data
Classifier: Development Status :: 3 - Alpha
Classifier: Intended Audience :: Developers
Classifier: License :: OSI Approved :: MIT License
Classifier: Programming Language :: Python :: 3
Classifier: Programming Language :: Python :: 3.6
Classifier: Programming Language :: Python :: 3.7
Classifier: Programming Language :: Python :: 3.8
Classifier: Programming Language :: Python :: 3.9
License-File: LICENCE.txt
Requires-Dist: plotly
Requires-Dist: plotly-express
Requires-Dist: matplotlib
Requires-Dist: scipy
Requires-Dist: pandas
Requires-Dist: numpy
Requires-Dist: scikit-learn
Requires-Dist: pyperclip
Requires-Dist: pyarrow
Requires-Dist: sas7bdat
Requires-Dist: pyreadstat
Requires-Dist: statsmodels
Requires-Dist: pyod
Requires-Dist: tensorflow
Requires-Dist: h5py
